Metadata-Version: 2.1
Name: django-simple-captcha
Version: 0.6.0
Summary: A very simple, yet powerful, Django captcha application
Home-page: https://github.com/mbi/django-simple-captcha
Author: Marco Bonetti
Author-email: mbonetti@gmail.com
License: MIT
Classifier: Development Status :: 4 - Beta
Classifier: Environment :: Web Environment
Classifier: Intended Audience :: Developers
Classifier: License :: OSI Approved :: MIT License
Classifier: Operating System :: OS Independent
Classifier: Programming Language :: Python
Classifier: Programming Language :: Python :: 3.9
Classifier: Programming Language :: Python :: 3.10
Classifier: Programming Language :: Python :: 3.11
Classifier: Programming Language :: Python :: 3.12
Classifier: Topic :: Security
Classifier: Topic :: Internet :: WWW/HTTP
Classifier: Framework :: Django
Provides-Extra: test
License-File: LICENSE
